setup.py
yqmiot.py
yqmiot.egg-info/PKG-INFO
yqmiot.egg-info/SOURCES.txt
yqmiot.egg-info/dependency_links.txt
yqmiot.egg-info/not-zip-safe
yqmiot.egg-info/requires.txt
yqmiot.egg-info/top_level.txt