Metadata-Version: 1.0
Name: yqmiot
Version: 1.0.1
Summary: the yqmiot client.
Home-page: http://yqmiot.com
Author: yueqiumao
Author-email: u2nn@qq.com
License: UNKNOWN
Keywords: yqmiot
Platform: UNKNOWN
